tests/__init__.py
viewstack/__init__.py
viewstack/__main__.py
viewstack/dto/__init__.py
viewstack/error/__init__.py
viewstack-0.0.2.dist-info/LICENSE
viewstack-0.0.2.dist-info/METADATA
viewstack-0.0.2.dist-info/WHEEL
viewstack-0.0.2.dist-info/entry_points.txt
viewstack-0.0.2.dist-info/top_level.txt
viewstack-0.0.2.dist-info/RECORD
