Metadata-Version: 2.1
Name: viewstack
Version: 0.0.2
Summary: Stack-based navigation for Python desktop apps
Home-page: https://github.com/pyrustic/viewstack
Author: Pyrustic Evangelist
Author-email: rusticalex@yahoo.com
Maintainer: Pyrustic Evangelist
Maintainer-email: rusticalex@yahoo.com
License: MIT
Keywords: application,pyrustic
Platform: UNKNOWN
Classifier: Programming Language :: Python :: 3
Classifier: License :: OSI Approved :: MIT License
Classifier: Operating System :: OS Independent
Requires-Python: >=3.5
License-File: LICENSE
Requires-Dist: viewable
